pathcrawler/__init__.py
pathcrawler/pathcrawler.py
pathcrawler-2.0.0.dist-info/METADATA
pathcrawler-2.0.0.dist-info/WHEEL
pathcrawler-2.0.0.dist-info/licenses/LICENSE.txt
pathcrawler-2.0.0.dist-info/RECORD
