Metadata-Version: 2.1
Name: pathcrawler
Version: 2.0.0
Summary: This used to be more useful when I didn't realize I could just rglob('*.*'). Leaving it up so I don't break my other projects/ format_size() is still convenient.
Project-URL: Homepage, https://github.com/matt-manes/pathcrawler
Project-URL: Documentation, https://github.com/matt-manes/pathcrawler/tree/main/docs
Project-URL: Source code, https://github.com/matt-manes/pathcrawler/tree/main/src/pathcrawler
Author: Matt Manes
License-File: LICENSE.txt
Keywords: directory
Classifier: License :: OSI Approved :: MIT License
Classifier: Operating System :: OS Independent
Classifier: Programming Language :: Python :: 3
Requires-Python: >=3.10
